funsor/__init__.py
funsor/adam.py
funsor/adjoint.py
funsor/affine.py
funsor/approximations.py
funsor/cnf.py
funsor/compiler.py
funsor/constant.py
funsor/delta.py
funsor/distribution.py
funsor/domains.py
funsor/elbo.py
funsor/factory.py
funsor/gaussian.py
funsor/instrument.py
funsor/integrate.py
funsor/interpretations.py
funsor/interpreter.py
funsor/joint.py
funsor/minipyro.py
funsor/montecarlo.py
funsor/op_factory.py
funsor/optimizer.py
funsor/precondition.py
funsor/recipes.py
funsor/registry.py
funsor/sum_product.py
funsor/syntax.py
funsor/tensor.py
funsor/terms.py
funsor/testing.py
funsor/typing.py
funsor/util.py
funsor/compat/__init__.py
funsor/compat/ops.py
funsor/einsum/__init__.py
funsor/einsum/numpy_log.py
funsor/einsum/numpy_map.py
funsor/einsum/util.py
funsor/jax/__init__.py
funsor/jax/distributions.py
funsor/jax/ops.py
funsor/ops/__init__.py
funsor/ops/array.py
funsor/ops/builtin.py
funsor/ops/op.py
funsor/ops/program.py
funsor/ops/tracer.py
funsor/pyro/__init__.py
funsor/pyro/convert.py
funsor/pyro/distribution.py
funsor/pyro/hmm.py
funsor/torch/__init__.py
funsor/torch/distributions.py
funsor/torch/ops.py
funsor/torch/provenance.py
funsor-0.4.5.dist-info/LICENSE.md
funsor-0.4.5.dist-info/METADATA
funsor-0.4.5.dist-info/WHEEL
funsor-0.4.5.dist-info/top_level.txt
funsor-0.4.5.dist-info/RECORD
