Metadata-Version: 2.1
Name: funsor
Version: 0.4.5
Summary: A tensor-like library for functions and distributions
Home-page: https://github.com/pyro-ppl/funsor
Author: Uber AI Labs
Project-URL: Documentation, https://funsor.pyro.ai
Keywords: probabilistic machine learning bayesian statistics pytorch jax
Classifier: Intended Audience :: Developers
Classifier: Intended Audience :: Education
Classifier: Intended Audience :: Science/Research
Classifier: License :: OSI Approved :: Apache Software License
Classifier: Operating System :: POSIX :: Linux
Classifier: Operating System :: MacOS :: MacOS X
Classifier: Programming Language :: Python :: 3.7
Classifier: Programming Language :: Python :: 3.8
Classifier: Programming Language :: Python :: 3.9
Classifier: Programming Language :: Python :: 3.10
Requires-Python: >=3.7
License-File: LICENSE.md
Requires-Dist: makefun
Requires-Dist: multipledispatch
Requires-Dist: numpy (>=1.7)
Requires-Dist: opt-einsum (>=2.3.2)
Requires-Dist: typing-extensions
Provides-Extra: dev
Requires-Dist: black ; extra == 'dev'
Requires-Dist: flake8 ; extra == 'dev'
Requires-Dist: isort (>=5.0) ; extra == 'dev'
Requires-Dist: nbsphinx ; extra == 'dev'
Requires-Dist: pandas ; extra == 'dev'
Requires-Dist: pillow (==8.2.0) ; extra == 'dev'
Requires-Dist: pytest (==4.3.1) ; extra == 'dev'
Requires-Dist: pytest-xdist (==1.27.0) ; extra == 'dev'
Requires-Dist: scipy ; extra == 'dev'
Requires-Dist: sphinx (>=2.0) ; extra == 'dev'
Requires-Dist: sphinx-gallery ; extra == 'dev'
Requires-Dist: sphinx-rtd-theme ; extra == 'dev'
Requires-Dist: torchvision (>=0.12.0) ; extra == 'dev'
Provides-Extra: jax
Requires-Dist: numpyro (>=0.7.0) ; extra == 'jax'
Requires-Dist: jax (>=0.2.21) ; extra == 'jax'
Requires-Dist: jaxlib (>=0.1.71) ; extra == 'jax'
Provides-Extra: test
Requires-Dist: black ; extra == 'test'
Requires-Dist: flake8 ; extra == 'test'
Requires-Dist: isort (>=5.0) ; extra == 'test'
Requires-Dist: pandas ; extra == 'test'
Requires-Dist: pillow (==8.2.0) ; extra == 'test'
Requires-Dist: pyro-api (>=0.1.2) ; extra == 'test'
Requires-Dist: pytest (==4.3.1) ; extra == 'test'
Requires-Dist: pytest-xdist (==1.27.0) ; extra == 'test'
Requires-Dist: requests ; extra == 'test'
Requires-Dist: scipy ; extra == 'test'
Requires-Dist: torchvision (>=0.12.0) ; extra == 'test'
Provides-Extra: torch
Requires-Dist: pyro-ppl (>=1.8.0) ; extra == 'torch'
Requires-Dist: torch (>=1.11.0) ; extra == 'torch'
